Metadata-Version: 1.0
Name: pumrapee-sample-distributions
Version: 0.1
Summary: Gaussian and Binomial distributions
Home-page: UNKNOWN
Author: Pumrapee Poomka
Author-email: pumrapee2599@gmail.com
License: UNKNOWN
Platform: UNKNOWN
